nswdesignsystem.plone6-0.4.3-py3.9-nspkg.pth
nswdesignsystem/plone6/__init__.py
nswdesignsystem/plone6/configure.zcml
nswdesignsystem/plone6/constants.py
nswdesignsystem/plone6/dependencies.zcml
nswdesignsystem/plone6/interfaces.py
nswdesignsystem/plone6/permissions.zcml
nswdesignsystem/plone6/setuphandlers.py
nswdesignsystem/plone6/testing.py
nswdesignsystem/plone6/upgrades.py
nswdesignsystem/plone6/upgrades.zcml
nswdesignsystem/plone6/browser/__init__.py
nswdesignsystem/plone6/browser/configure.zcml
nswdesignsystem/plone6/browser/controlpanel.py
nswdesignsystem/plone6/browser/overrides/.gitkeep
nswdesignsystem/plone6/browser/static/.gitkeep
nswdesignsystem/plone6/locales/README.rst
nswdesignsystem/plone6/locales/__init__.py
nswdesignsystem/plone6/locales/nswdesignsystem.plone6.pot
nswdesignsystem/plone6/locales/update.py
nswdesignsystem/plone6/locales/update.sh
nswdesignsystem/plone6/locales/en/LC_MESSAGES/nswdesignsystem.plone6.po
nswdesignsystem/plone6/profiles/default/browserlayer.xml
nswdesignsystem/plone6/profiles/default/catalog.xml
nswdesignsystem/plone6/profiles/default/controlpanel.xml
nswdesignsystem/plone6/profiles/default/metadata.xml
nswdesignsystem/plone6/profiles/default/registry/main.xml
nswdesignsystem/plone6/profiles/uninstall/browserlayer.xml
nswdesignsystem/plone6/restapi/__init__.py
nswdesignsystem/plone6/restapi/configure.zcml
nswdesignsystem/plone6/restapi/get.py
nswdesignsystem/plone6/restapi/serializer/__init__.py
nswdesignsystem/plone6/restapi/serializer/configure.zcml
nswdesignsystem/plone6/restapi/serializer/nsw_site_settings.py
nswdesignsystem/plone6/tests/__init__.py
nswdesignsystem/plone6/tests/test_robot.py
nswdesignsystem/plone6/tests/test_setup.py
nswdesignsystem/plone6/tests/robot/test_example.robot
nswdesignsystem.plone6-0.4.3.dist-info/LICENSE.GPL
nswdesignsystem.plone6-0.4.3.dist-info/LICENSE.rst
nswdesignsystem.plone6-0.4.3.dist-info/METADATA
nswdesignsystem.plone6-0.4.3.dist-info/WHEEL
nswdesignsystem.plone6-0.4.3.dist-info/entry_points.txt
nswdesignsystem.plone6-0.4.3.dist-info/namespace_packages.txt
nswdesignsystem.plone6-0.4.3.dist-info/top_level.txt
nswdesignsystem.plone6-0.4.3.dist-info/RECORD
