Metadata-Version: 2.1
Name: nswdesignsystem.plone6
Version: 0.4.3
Summary: Plone backend package for the NSW Design system
Home-page: https://github.com/collective/nswdesignsystem.plone6
Author: PretaGov
Author-email: jeff.bledsoe@pretagov.com.au
License: GPL version 2
Project-URL: PyPI, https://pypi.python.org/pypi/nswdesignsystem.plone6
Project-URL: Source, https://github.com/collective/nswdesignsystem.plone6
Project-URL: Tracker, https://github.com/collective/nswdesignsystem.plone6/issues
Keywords: Python Plone CMS
Classifier: Development Status :: 4 - Beta
Classifier: Environment :: Web Environment
Classifier: Framework :: Plone
Classifier: Framework :: Plone :: Addon
Classifier: Framework :: Plone :: 6.0
Classifier: Programming Language :: Python
Classifier: Programming Language :: Python :: 3.9
Classifier: Programming Language :: Python :: 3.10
Classifier: Programming Language :: Python :: 3.11
Classifier: Operating System :: OS Independent
Classifier: License :: OSI Approved :: GNU General Public License v2 (GPLv2)
Requires-Python: >=3.9, <3.12
License-File: LICENSE.GPL
License-File: LICENSE.rst
Requires-Dist: setuptools
Requires-Dist: z3c.jbot
Requires-Dist: plone.app.registry
Requires-Dist: plone.autoform
Requires-Dist: plone.base
Requires-Dist: plone.api >=1.8.4
Requires-Dist: plone.restapi
Requires-Dist: plone.supermodel
Requires-Dist: Products.GenericSetup
Requires-Dist: collective.volto.formsupport
Requires-Dist: collective.volto.formsupport[recaptcha]
Requires-Dist: collective.volto.formsupport[honeypot]
Requires-Dist: collective.volto.subfooter ==1.1.0
Provides-Extra: release
Requires-Dist: zest.releaser[recommended] ; extra == 'release'
Requires-Dist: zestreleaser.towncrier ; extra == 'release'
Provides-Extra: test
Requires-Dist: plone.app.testing ; extra == 'test'
Requires-Dist: plone.app.dexterity ; extra == 'test'
Requires-Dist: plone.browserlayer ; extra == 'test'
Requires-Dist: plone.testing >=5.0.0 ; extra == 'test'
Requires-Dist: robotsuite ; extra == 'test'
Requires-Dist: plone.app.robotframework[debug] ; extra == 'test'
